telegram_logger/__init__.py
telegram_logger-0.0.1.dist-info/LICENSE
telegram_logger-0.0.1.dist-info/METADATA
telegram_logger-0.0.1.dist-info/WHEEL
telegram_logger-0.0.1.dist-info/top_level.txt
telegram_logger-0.0.1.dist-info/RECORD
