Metadata-Version: 2.1
Name: telegram-logger
Version: 0.0.1
Summary: Package allowing to log directly to Telegram
Home-page: https://github.com/Beaxhem/telegram_logger
Author: beaxhem
Author-email: senchukov02@gmail.com
License: mit
Platform: UNKNOWN
Classifier: Programming Language :: Python :: 3
Classifier: License :: OSI Approved :: MIT License
Classifier: Operating System :: OS Independent
Requires-Python: >=3.6
